toot/__init__.py
toot/__main__.py
toot/api.py
toot/auth.py
toot/cache.py
toot/config.py
toot/entities.py
toot/exceptions.py
toot/http.py
toot/logging.py
toot/output.py
toot/settings.py
toot/wcstring.py
toot/cli/__init__.py
toot/cli/accounts.py
toot/cli/auth.py
toot/cli/diag.py
toot/cli/follow_requests.py
toot/cli/lists.py
toot/cli/polls.py
toot/cli/post.py
toot/cli/read.py
toot/cli/statuses.py
toot/cli/tags.py
toot/cli/timelines.py
toot/cli/timelines_v2.py
toot/cli/tui.py
toot/cli/validators.py
toot/tui/NOTES.md
toot/tui/__init__.py
toot/tui/app.py
toot/tui/compose.py
toot/tui/constants.py
toot/tui/entities.py
toot/tui/images.py
toot/tui/overlays.py
toot/tui/poll.py
toot/tui/scroll.py
toot/tui/timeline.py
toot/tui/utils.py
toot/tui/widgets.py
toot/tui/richtext/__init__.py
toot/tui/richtext/richtext.py
toot/urwidgets/README.md
toot/urwidgets/__init__.py
toot/urwidgets/hyperlink.py
toot/urwidgets/text_embed.py
toot/utils/__init__.py
toot/utils/datetime.py
toot/utils/language.py
toot-0.51.0.dist-info/licenses/LICENSE
toot-0.51.0.dist-info/METADATA
toot-0.51.0.dist-info/WHEEL
toot-0.51.0.dist-info/entry_points.txt
toot-0.51.0.dist-info/top_level.txt
toot-0.51.0.dist-info/RECORD
