Metadata-Version: 2.4
Name: toot
Version: 0.51.0
Summary: Mastodon CLI client
Author-email: Ivan Habunek <ivan@habunek.com>
License-Expression: GPL-3.0-only
Project-URL: Homepage, https://toot.bezdomni.net
Project-URL: Source, https://github.com/ihabunek/toot/
Classifier: Environment :: Console :: Curses
Classifier: Environment :: Console
Classifier: Operating System :: OS Independent
Classifier: Programming Language :: Python :: 3
Requires-Python: >=3.9
License-File: LICENSE
Requires-Dist: beautifulsoup4<5.0,>=4.5.0
Requires-Dist: click~=8.1
Requires-Dist: python-dateutil<3.0,>=2.8.1
Requires-Dist: requests<3.0,>=2.13
Requires-Dist: tomlkit<1.0,>=0.10.0
Requires-Dist: urwid~=3.0
Requires-Dist: wcwidth>=0.1.7
Provides-Extra: images
Requires-Dist: pillow>=9.5.0; extra == "images"
Requires-Dist: term-image>=0.7.2; extra == "images"
Dynamic: license-file
